{"_default": {"1": {"comment": "I love this coffee", "rating": 5, "customer_id": "Maria", "date": 1433046611.546895, "stars": [1, 1, 1, 1, 1]}, "2": {"comment": "Nice flavor", "rating": 4, "customer_id": "Phillips", "date": 1433046611.547154, "stars": [1, 1, 1, 1, 0]}, "3": {"comment": "One of my fav coffees", "rating": 2, "customer_id": "Young", "date": 1433046611.547433, "stars": [1, 1, 0, 0, 0]}, "4": {"comment": "Baristas are really nice at Philz", "rating": 2, "customer_id": "Nathan", "date": 1433046611.547776, "stars": [1, 1, 0, 0, 0]}}}